<?xml version="1.0"?>
<extension key="au.com.agileware.expiredcreditcards" type="module">
  <file>expiredcreditcards</file>
  <name>Expired Credit Cards</name>
  <description>This extension checks expired credit cards of the user.</description>
  <license>AGPL-3.0</license>
  <maintainer>
    <author>Agileware</author>
    <email>support@agileware.com.au</email>
  </maintainer>
  <urls>
    <url desc="Main Extension Page">https://bitbucket.org/agileware/au.com.agileware.expiredcreditcards</url>
    <url desc="Documentation">https://bitbucket.org/agileware/au.com.agileware.expiredcreditcards/blob/master/README.md</url>
    <url desc="Support">https://agileware.com.au/contact</url>
    <url desc="Licensing">http://www.gnu.org/licenses/agpl-3.0.html</url>
  </urls>
  <releaseDate>2019-04-29</releaseDate>
  <version>1.0</version>
  <compatibility>
    <ver>5.0</ver>
  </compatibility>
  <civix>
    <namespace>CRM/Expiredcreditcards</namespace>
  </civix>
</extension>
